Metadata-Version: 2.1
Name: standardwebhooks
Version: 1.0.0
Summary: Standard Webhooks
Author: Standard Webhooks
License: MIT
Keywords: webhooks
Classifier: Intended Audience :: Developers
Classifier: Intended Audience :: Information Technology
Classifier: Operating System :: OS Independent
Classifier: Programming Language :: Python :: 3
Classifier: Programming Language :: Python
Classifier: Topic :: Software Development :: Libraries :: Application Frameworks
Classifier: Topic :: Software Development :: Libraries :: Python Modules
Classifier: Topic :: Software Development :: Libraries
Classifier: Topic :: Software Development
Classifier: Typing :: Typed
Classifier: License :: OSI Approved :: MIT License
Classifier: Programming Language :: Python :: 3 :: Only
Classifier: Programming Language :: Python :: 3.6
Classifier: Programming Language :: Python :: 3.7
Classifier: Programming Language :: Python :: 3.8
Requires-Python: >=3.6
Requires-Dist: httpx>=0.23.0
Requires-Dist: attrs>=21.3.0
Requires-Dist: python-dateutil
Requires-Dist: Deprecated
Requires-Dist: types-python-dateutil
Requires-Dist: types-Deprecated
